{
  "string": [
    {
      "name": "app_name",
      "value": "Location"
    },
    {
      "name": "mainability_description",
      "value": "hap sample empty page"
    },
    {
      "name": "reason_description",
      "value": "location sample get permisssion"
    },
    {
      "name": "start_location",
      "value": "Start Location"
    },
    {
      "name": "stop_location",
      "value": "Stop Location"
    },
    {
      "name": "location_info",
      "value": "Location Info"
    },
    {
      "name": "geo_address_info",
      "value": " Geo Address Info"
    }
  ]
}