{
  "string": [
    {
      "name": "app_name",
      "value": "AudioPlayer"
    },
    {
      "name": "mainability_description",
      "value": "hap sample empty page"
    },
    {
      "name": "to_previous",
      "value": "<"
    },
    {
      "name": "play",
      "value": "PLAY"
    },
    {
      "name": "to_next",
      "value": ">"
    },
    {
      "name": "pause",
      "value": "||"
    },
    {
      "name": "jump",
      "value": "TO PLAY ONLINE AUDIO"
    },
    {
      "name": "slash",
      "value": "/"
    },
    {
      "name": "http",
      "value": "https://"
    }
  ]
}